sakurs-0.1.1.dist-info/METADATA
sakurs-0.1.1.dist-info/WHEEL
sakurs/__init__.py
sakurs/__init__.pyi
sakurs/py.typed
sakurs/sakurs.abi3.so
sakurs-0.1.1.dist-info/RECORD
