Metadata-Version: 2.4
Name: sakurs
Version: 0.1.1
Classifier: Development Status :: 3 - Alpha
Classifier: Intended Audience :: Developers
Classifier: License :: OSI Approved :: MIT License
Classifier: Programming Language :: Python :: 3
Classifier: Programming Language :: Python :: 3.9
Classifier: Programming Language :: Python :: 3.10
Classifier: Programming Language :: Python :: 3.11
Classifier: Programming Language :: Python :: 3.12
Classifier: Programming Language :: Rust
Classifier: Topic :: Text Processing
Classifier: Topic :: Text Processing :: Linguistic
Requires-Dist: ruff>=0.12.0,<0.13.0 ; extra == 'dev'
Requires-Dist: mypy~=1.0 ; extra == 'dev'
Requires-Dist: types-setuptools ; extra == 'dev'
Requires-Dist: pytest~=7.0 ; extra == 'test'
Requires-Dist: pytest-cov~=4.0 ; extra == 'test'
Requires-Dist: hypothesis~=6.0 ; extra == 'test'
Requires-Dist: pytest~=7.0 ; extra == 'benchmark'
Requires-Dist: pytest-benchmark~=4.0 ; extra == 'benchmark'
Requires-Dist: pysbd~=0.3.4 ; extra == 'benchmark'
Requires-Dist: ja-sentence-segmenter~=0.0.2 ; extra == 'benchmark'
Requires-Dist: pytest-md-report~=0.5.0 ; extra == 'benchmark'
Provides-Extra: dev
Provides-Extra: test
Provides-Extra: benchmark
Summary: Fast, parallel sentence boundary detection using Delta-Stack Monoid algorithm
Keywords: nlp,sentence,boundary,detection,tokenization,parallel
Home-Page: https://github.com/sog4be/sakurs
Author: sog4be <163720533+sog4be@users.noreply.github.com>
Author-email: Ryo Sogabe <163720533+sog4be@users.noreply.github.com>
License: MIT
Requires-Python: >=3.9
Project-URL: Repository, https://github.com/sog4be/sakurs
Project-URL: Documentation, https://github.com/sog4be/sakurs#readme
Project-URL: Issues, https://github.com/sog4be/sakurs/issues
